project/__init__.py
project/main.py
project/data/__init__.py
project/data/address_book_functions.py
project/data/classes.py
project/data/global_declarations.py
project/data/notebook_functions.py
simon_bot-0.5.dist-info/METADATA
simon_bot-0.5.dist-info/WHEEL
simon_bot-0.5.dist-info/entry_points.txt
simon_bot-0.5.dist-info/top_level.txt
simon_bot-0.5.dist-info/RECORD
