Metadata-Version: 2.1
Name: simon-bot
Version: 0.5
Requires-Dist: prompt-toolkit
